[
  {
    "name": "Очередь на МАПП",
    "type": "TERMINAL"
  },
  {
    "name": "Ожидание выгрузки контейнера из поезда",
    "type": "TERMINAL"
  },
  {
    "name": "Смещение выхода судов",
    "type": "PORT"
  },
  {
    "name": "Длительная швартовка судна",
    "type": "PORT"
  },
  {
    "name": "«Завал» контейнера в порту",
    "type": "PORT"
  },
  {
    "name": "Тряска при погрузке на морское судно",
    "type": "PORT"
  },
  {
    "name": "Погодные условия",
    "type": "ALL"
  },
  {
    "name": "Обстоятельства непреодолимой силы (военные действия, стихийные бедствия, эпидемии)",
    "type": "ALL"
  },
  {
    "name": "Административные запреты пропуска грузов",
    "type": "ALL"
  },
  {
    "name": "Ожидание подвода платформ",
    "type": "ALL"
  },
  {
    "name": "Простой на погранпереходе в ожидании перегрузки",
    "type": "ALL"
  },
  {
    "name": "Перенос рейса",
    "type": "ALL"
  },
  {
    "name": "Технические проблемы в работе транспорта",
    "type": "ALL"
  },
  {
    "name": "Ошибки в транспортных документах, неверно заполненная документация",
    "type": "ALL"
  },
  {
    "name": "Повышенный трафик на дорогах",
    "type": "ALL"
  },
  {
    "name": "Простои автомобилей/ждт/шиппингового оборудования в ожидании ПРО",
    "type": "ALL"
  },
  {
    "name": "Повреждение груза водой, пожаром или механическим воздействием",
    "type": "ALL"
  },
  {
    "name": "Изменение курса валюты за рубежом",
    "type": "ALL"
  },
  {
    "name": "Закрытие границ государства",
    "type": "ALL"
  },
  {
    "name": "Непредвиденное снижение объема заявки на покупку продукции",
    "type": "ALL"
  },
  {
    "name": "Невыдача или задержка выдачи груза клиентом",
    "type": "ALL"
  }
]